ssctl/__init__.py
ssctl/action/__init__.py
ssctl/action/add/__init__.py
ssctl/action/delete/__init__.py
ssctl/action/init/__init__.py
ssctl/base/__init__.py
ssctl/base/logger.py
ssctl/base/supervisor.py
ssctl/base/system.py
ssctl/base/yum.py
ssctl-0.2.1.dist-info/LICENSE
ssctl-0.2.1.dist-info/METADATA
ssctl-0.2.1.dist-info/WHEEL
ssctl-0.2.1.dist-info/entry_points.txt
ssctl-0.2.1.dist-info/top_level.txt
ssctl-0.2.1.dist-info/RECORD
