Metadata-Version: 2.1
Name: ssctl
Version: 0.2.1
Summary: shadowsocks 部署工具
Home-page: http://10.0.0.100:81/anyu/proxy_admin
Author: Tim Tam
Author-email: timtamtamtim@yandex.com
License: BSD
Keywords: ss
Platform: Linux
Classifier: Development Status :: 2 - Pre-Alpha
Classifier: Topic :: Software Development :: Build Tools
Classifier: License :: OSI Approved :: BSD License
Classifier: Topic :: System :: Distributed Computing
Classifier: Programming Language :: Python
Classifier: Programming Language :: Python :: 2
Classifier: Programming Language :: Python :: 2.7
Classifier: Programming Language :: Python :: 3
Classifier: Programming Language :: Python :: 3.5
Classifier: Programming Language :: Python :: 3.6
Classifier: Programming Language :: Python :: 3.7
Classifier: Programming Language :: Python :: 3.8
Classifier: Programming Language :: Python :: Implementation :: PyPy
Classifier: Operating System :: POSIX :: Linux
Requires-Python: >=2.7, !=3.0.*, !=3.1.*, !=3.2.*, !=3.3.*, !=3.4.*
